s3ftp/__init__.py
s3ftp/protocol.py
s3ftp/shells.py
s3ftp/test/__init__.py
s3ftp-0.1.2.dist-info/DESCRIPTION.rst
s3ftp-0.1.2.dist-info/entry_points.txt
s3ftp-0.1.2.dist-info/METADATA
s3ftp-0.1.2.dist-info/pydist.json
s3ftp-0.1.2.dist-info/RECORD
s3ftp-0.1.2.dist-info/top_level.txt
s3ftp-0.1.2.dist-info/WHEEL
