Metadata-Version: 2.0
Name: s3ftp
Version: 0.1.2
Summary: FTP server with S3 backend
Home-page: https://github.com/GaretJax/s3ftp
Author: Jonathan Stoppani
Author-email: jonathan@stoppani.name
License: MIT
Platform: UNKNOWN
Classifier: Development Status :: 4 - Beta
Classifier: Intended Audience :: Developers
Classifier: License :: OSI Approved :: MIT License
Classifier: Operating System :: OS Independent
Classifier: Programming Language :: Python
Classifier: Topic :: Software Development :: Libraries :: Python Modules
